X7TianXuehuiPhpQianfengJiaoyu/README.md
X7TianXuehuiPhpQianfengJiaoyu/__init__.py
X7TianXuehuiPhpQianfengJiaoyu/__main__.py
X7TianXuehuiPhpQianfengJiaoyu/file.epub
X7TianXuehuiPhpQianfengJiaoyu/index.html
X7TianXuehuiPhpQianfengJiaoyu/css/__init__.py
X7TianXuehuiPhpQianfengJiaoyu/css/annotations.css
X7TianXuehuiPhpQianfengJiaoyu/css/main.css
X7TianXuehuiPhpQianfengJiaoyu/css/normalize.css
X7TianXuehuiPhpQianfengJiaoyu/css/popup.css
X7TianXuehuiPhpQianfengJiaoyu/font/__init__.py
X7TianXuehuiPhpQianfengJiaoyu/font/fontello.eot
X7TianXuehuiPhpQianfengJiaoyu/font/fontello.svg
X7TianXuehuiPhpQianfengJiaoyu/font/fontello.ttf
X7TianXuehuiPhpQianfengJiaoyu/font/fontello.woff
X7TianXuehuiPhpQianfengJiaoyu/img/__init__.py
X7TianXuehuiPhpQianfengJiaoyu/img/annotator-glyph-sprite.png
X7TianXuehuiPhpQianfengJiaoyu/img/annotator-icon-sprite.png
X7TianXuehuiPhpQianfengJiaoyu/img/apple-touch-icon.png
X7TianXuehuiPhpQianfengJiaoyu/img/cancelfullscreen.png
X7TianXuehuiPhpQianfengJiaoyu/img/close.png
X7TianXuehuiPhpQianfengJiaoyu/img/fullscreen.png
X7TianXuehuiPhpQianfengJiaoyu/img/loader.gif
X7TianXuehuiPhpQianfengJiaoyu/img/menu-icon.png
X7TianXuehuiPhpQianfengJiaoyu/img/save.png
X7TianXuehuiPhpQianfengJiaoyu/img/saved.png
X7TianXuehuiPhpQianfengJiaoyu/img/settings-s.png
X7TianXuehuiPhpQianfengJiaoyu/img/settings.png
X7TianXuehuiPhpQianfengJiaoyu/img/star.png
X7TianXuehuiPhpQianfengJiaoyu/js/__init__.py
X7TianXuehuiPhpQianfengJiaoyu/js/epub.js
X7TianXuehuiPhpQianfengJiaoyu/js/epub.min.js
X7TianXuehuiPhpQianfengJiaoyu/js/epub.min.map
X7TianXuehuiPhpQianfengJiaoyu/js/hooks.min.js
X7TianXuehuiPhpQianfengJiaoyu/js/hooks.min.map
X7TianXuehuiPhpQianfengJiaoyu/js/reader.js
X7TianXuehuiPhpQianfengJiaoyu/js/reader.js.map
X7TianXuehuiPhpQianfengJiaoyu/js/reader.min.js
X7TianXuehuiPhpQianfengJiaoyu/js/reader.min.map
X7TianXuehuiPhpQianfengJiaoyu/js/hooks/__init__.py
X7TianXuehuiPhpQianfengJiaoyu/js/hooks/extensions/__init__.py
X7TianXuehuiPhpQianfengJiaoyu/js/hooks/extensions/highlight.js
x7_tian_xuehui_php_qianfeng_jiaoyu-2024.3.2.0.dist-info/METADATA
x7_tian_xuehui_php_qianfeng_jiaoyu-2024.3.2.0.dist-info/WHEEL
x7_tian_xuehui_php_qianfeng_jiaoyu-2024.3.2.0.dist-info/entry_points.txt
x7_tian_xuehui_php_qianfeng_jiaoyu-2024.3.2.0.dist-info/top_level.txt
x7_tian_xuehui_php_qianfeng_jiaoyu-2024.3.2.0.dist-info/RECORD
